tests/__init__.py
tests/test_core.py
tests/test_decorators.py
travel_debugger-1.1.0.dist-info/licenses/LICENSE
travel_debugger-1.1.0.dist-info/METADATA
travel_debugger-1.1.0.dist-info/WHEEL
travel_debugger-1.1.0.dist-info/entry_points.txt
travel_debugger-1.1.0.dist-info/top_level.txt
travel_debugger-1.1.0.dist-info/RECORD
